atividade_algoritmos/__init__.py
atividade_algoritmos/arvore_de_espalhamento_minimo/__init__.py
atividade_algoritmos/caminho_minimo/__init__.py
atividades_algoritmos-0.1.dist-info/AUTHORS
atividades_algoritmos-0.1.dist-info/LICENSE
atividades_algoritmos-0.1.dist-info/METADATA
atividades_algoritmos-0.1.dist-info/WHEEL
atividades_algoritmos-0.1.dist-info/top_level.txt
atividades_algoritmos-0.1.dist-info/RECORD
