Metadata-Version: 2.1
Name: atividades-algoritmos
Version: 0.1
Summary: Pacote com a resolução das atividades do segundo estágio
Home-page: https://github.com/JhonnathaAndrade/atividades_algoritmos
Author: Jhonnatha de Andrade Monteiro
Author-email: jhonnatha.am@gmail.com
License: MIT
Keywords: algorithms,python
Platform: UNKNOWN
Classifier: Development Status :: 3 - Alpha
Classifier: Intended Audience :: Developers
Classifier: Intended Audience :: Education
Classifier: Intended Audience :: Science/Research
Classifier: License :: OSI Approved :: MIT License
Classifier: Natural Language :: Portuguese
Classifier: Operating System :: MacOS
Classifier: Operating System :: Microsoft :: Windows
Classifier: Operating System :: POSIX
Classifier: Operating System :: POSIX :: BSD
Classifier: Operating System :: POSIX :: Linux
Classifier: Operating System :: Unix
Classifier: Programming Language :: Python
Classifier: Programming Language :: Python :: 3.6
Classifier: Programming Language :: Python :: Implementation :: CPython
Classifier: Topic :: Education
